dtree/__init__.py
dtree/dtree.py
dtree/run.sh
dtree_metalcycling-0.4.2.dist-info/METADATA
dtree_metalcycling-0.4.2.dist-info/WHEEL
dtree_metalcycling-0.4.2.dist-info/licenses/LICENSE
dtree_metalcycling-0.4.2.dist-info/RECORD
