Metadata-Version: 2.4
Name: dtree-metalcycling
Version: 0.4.2
Summary: 'dtree': Linux 'tree' but for Python dictionaries
License-File: LICENSE
Keywords: dictionary,tree
Requires-Dist: colorama
Requires-Dist: omegaconf
